gaul/__init__.py
gaul/advi.py
gaul/hmc.py
gaul/quap.py
gaul/types.py
gaul/utils/__init__.py
gaul/utils/pbar.py
gaul/utils/tree_utils.py
gaul-0.4.2.dist-info/WHEEL
gaul-0.4.2.dist-info/METADATA
gaul-0.4.2.dist-info/RECORD
