Metadata-Version: 2.1
Name: gaul
Version: 0.4.2
Summary: 
Home-page: https://github.com/al-jshen/gaul
License: MIT OR Apache-2.0
Keywords: jax
Author: Jeff Shen
Author-email: jshen2014@hotmail.com
Requires-Python: >=3.7.1,<3.11
Classifier: License :: Other/Proprietary License
Classifier: Programming Language :: Python :: 3
Classifier: Programming Language :: Python :: 3.8
Classifier: Programming Language :: Python :: 3.9
Classifier: Programming Language :: Python :: 3.10
Requires-Dist: jax (>=0.3.1,<0.4.0)
Requires-Dist: jaxlib (>=0.3.0,<0.4.0)
Requires-Dist: tqdm (>=4.62.3,<5.0.0)
Project-URL: Documentation, https://gaul.readthedocs.io
Project-URL: Repository, https://github.com/al-jshen/gaul
